oneNeuron/__init__.py
oneNeuron/perceptron.py
oneNeuron_Pypi_Suresh_Singamsetty-0.0.1.dist-info/LICENSE
oneNeuron_Pypi_Suresh_Singamsetty-0.0.1.dist-info/METADATA
oneNeuron_Pypi_Suresh_Singamsetty-0.0.1.dist-info/WHEEL
oneNeuron_Pypi_Suresh_Singamsetty-0.0.1.dist-info/top_level.txt
oneNeuron_Pypi_Suresh_Singamsetty-0.0.1.dist-info/RECORD
